{"name":"build-javascript","namedChunkGroups":{"app":{"name":"app","assets":[{"name":"webpack-runtime-0b2ac016b092e87f7c94.js","size":3982},{"name":"framework-0d657d37116af3e14284.js","size":209872},{"name":"styles.955f8a32cdea0b8cd858.css","size":15598},{"name":"app-04925bc04bffd0e6cca5.js","size":69629}],"filteredAssets":0,"assetsSize":299081,"filteredAuxiliaryAssets":55,"auxiliaryAssetsSize":1887411},"gatsby-plugin-image":{"name":"gatsby-plugin-image","assets":[{"name":"gatsby-plugin-image-e42b77adf226207a5111.js","size":18535}],"filteredAssets":0,"assetsSize":18535,"filteredAuxiliaryAssets":1,"auxiliaryAssetsSize":78184},"component---src-pages-404-js":{"name":"component---src-pages-404-js","assets":[{"name":"commons-d87a4b40c9b1aee83ba3.js","size":47666},{"name":"component---src-pages-404-js-89cf17fad23343c87c0a.js","size":567}],"filteredAssets":0,"assetsSize":48233,"filteredAuxiliaryAssets":2,"auxiliaryAssetsSize":197229},"component---src-pages-index-js":{"name":"component---src-pages-index-js","assets":[{"name":"commons-d87a4b40c9b1aee83ba3.js","size":47666},{"name":"component---src-pages-index-js-4d3140078e7573f3e094.js","size":1116}],"filteredAssets":0,"assetsSize":48782,"filteredAuxiliaryAssets":2,"auxiliaryAssetsSize":199148}},"assetsByChunkName":{"app":["webpack-runtime-0b2ac016b092e87f7c94.js","framework-0d657d37116af3e14284.js","styles.955f8a32cdea0b8cd858.css","app-04925bc04bffd0e6cca5.js"],"gatsby-plugin-image":["gatsby-plugin-image-e42b77adf226207a5111.js"],"component---src-pages-404-js":["commons-d87a4b40c9b1aee83ba3.js","component---src-pages-404-js-89cf17fad23343c87c0a.js"],"component---src-pages-index-js":["commons-d87a4b40c9b1aee83ba3.js","component---src-pages-index-js-4d3140078e7573f3e094.js"]},"childAssetsByChunkName":{}}